{"nodes":[{"id":"schemas_passport","label":"passport.py","file_type":"code","source_file":"backend/app/schemas/passport.py","source_location":"L1"},{"id":"schemas_passport_fieldprovenance","label":"FieldProvenance","file_type":"code","source_file":"backend/app/schemas/passport.py","source_location":"L4"},{"id":"basemodel","label":"BaseModel","file_type":"code","source_file":"","source_location":""},{"id":"schemas_passport_companypassport","label":"CompanyPassport","file_type":"code","source_file":"backend/app/schemas/passport.py","source_location":"L15"}],"edges":[{"source":"schemas_passport","target":"typing","relation":"imports_from","confidence":"EXTRACTED","source_file":"backend/app/schemas/passport.py","source_location":"L1","weight":1},{"source":"schemas_passport","target":"pydantic","relation":"imports_from","confidence":"EXTRACTED","source_file":"backend/app/schemas/passport.py","source_location":"L2","weight":1},{"source":"schemas_passport","target":"schemas_passport_fieldprovenance","relation":"contains","confidence":"EXTRACTED","source_file":"backend/app/schemas/passport.py","source_location":"L4","weight":1},{"source":"schemas_passport_fieldprovenance","target":"basemodel","relation":"inherits","confidence":"EXTRACTED","source_file":"backend/app/schemas/passport.py","source_location":"L4","weight":1},{"source":"schemas_passport","target":"schemas_passport_companypassport","relation":"contains","confidence":"EXTRACTED","source_file":"backend/app/schemas/passport.py","source_location":"L15","weight":1},{"source":"schemas_passport_companypassport","target":"basemodel","relation":"inherits","confidence":"EXTRACTED","source_file":"backend/app/schemas/passport.py","source_location":"L15","weight":1}]}